gui_automation/__init__.py
gui_automation/background_handler.py
gui_automation/detector.py
gui_automation/foreground_handler.py
gui_automation/gui_automation.py
gui_automation/handler.py
gui_automation/image_detector.py
gui_automation/image_loader.py
gui_automation/spot.py
gui_automation-3.2.1.dist-info/LICENSE
gui_automation-3.2.1.dist-info/METADATA
gui_automation-3.2.1.dist-info/WHEEL
gui_automation-3.2.1.dist-info/top_level.txt
gui_automation-3.2.1.dist-info/RECORD
