Metadata-Version: 2.1
Name: gui-automation
Version: 3.2.1
Summary: Simple python library useful for automating tasks using images.
Home-page: https://github.com/marcosboggia/gui_automation
Author: Marcos Boggia
Author-email: marcos_boggia@hotmail.com
License: UNKNOWN
Platform: UNKNOWN
Classifier: Programming Language :: Python :: 3
Classifier: License :: OSI Approved :: MIT License
Classifier: Operating System :: OS Independent
Requires-Dist: numpy
Requires-Dist: opencv-python
Requires-Dist: PyAutoGUI
Requires-Dist: imutils
Requires-Dist: pywin32
Requires-Dist: pywin32-ctypes
Requires-Dist: pywinauto
